hamel_tools/__init__.py
hamel_tools/annotate_talk.py
hamel_tools/chapters.py
hamel_tools/transcribe.py
hamel_tools-0.2.0.dist-info/METADATA
hamel_tools-0.2.0.dist-info/WHEEL
hamel_tools-0.2.0.dist-info/entry_points.txt
hamel_tools-0.2.0.dist-info/RECORD
