Metadata-Version: 2.4
Name: hamel_tools
Version: 0.2.0
Summary: CLI tools for YouTube transcripts, chapters, and annotated talks
Author-email: Hamel Husain <hamel.husain@gmail.com>
License: MIT
Requires-Python: >=3.9
Requires-Dist: fastcore
Requires-Dist: google-genai
Requires-Dist: hamel
Requires-Dist: httpx
Requires-Dist: rich
Requires-Dist: typer
Requires-Dist: youtube-transcript-api
